fseg/__init__.py
fseg/_analyzer.py
fseg/_data.py
fseg/_version.py
fseg/impl/__init__.py
fseg/impl/_fseg.cpython-310-darwin.so
fseg/impl/libdate-tz.3.0.0.dylib
fseg/impl/libdate-tz.3.dylib
fseg/impl/libdate-tz.dylib
fseg/impl/libspa.dylib
fseg-0.8.0.dist-info/AUTHORS.md
fseg-0.8.0.dist-info/LICENSE
fseg-0.8.0.dist-info/METADATA
fseg-0.8.0.dist-info/WHEEL
fseg-0.8.0.dist-info/top_level.txt
fseg-0.8.0.dist-info/RECORD
