Metadata-Version: 2.1
Name: fseg
Version: 0.8.0
Summary: A python wrapper of algorithms for sun-earth geometry 
Author-email: Mike Song <gnosoir@hotmail.com>
License: LGPL-2.1
Project-URL: Homepage, https://mikesongming.github.io/SE-Geometry
Platform: cp310-macosx-10_12-x86_64
Platform: cp310-manylinux2014_x86_64
Platform: cp310-win_amd64
Classifier: Development Status :: 2 - Pre-Alpha
Classifier: Environment :: MacOS X
Classifier: Intended Audience :: Developers
Classifier: License :: OSI Approved :: GNU Lesser General Public License v2 or later (LGPLv2+)
Classifier: Operating System :: MacOS
Classifier: Programming Language :: C++
Classifier: Programming Language :: Python :: 3.10
Classifier: Programming Language :: Python :: Implementation :: CPython
Classifier: Topic :: Scientific/Engineering :: Astronomy
Classifier: Topic :: Scientific/Engineering :: GIS
Requires-Python: >=3.10
License-File: LICENSE
License-File: AUTHORS.md
